AUTHORS
LICENSE
README.md
setup.py
petextgrid/__init__.py
petextgrid/exceptions.py
petextgrid/textgrid.py
petextgrid.egg-info/PKG-INFO
petextgrid.egg-info/SOURCES.txt
petextgrid.egg-info/dependency_links.txt
petextgrid.egg-info/top_level.txt