Metadata-Version: 2.1
Name: petextgrid
Version: 0.0.3
Summary: Praat TextGrid manipulation.
Author: blank
Author-email: shanandone@qq.com
License-File: LICENSE
License-File: AUTHORS
